testlib.py
pyinnotemp/__init__.py
pyinnotemp/connector.py
pyinnotemp/rooms.py
pyinnotemp/system.py
pyinnotemp-0.2.dist-info/LICENSE
pyinnotemp-0.2.dist-info/METADATA
pyinnotemp-0.2.dist-info/WHEEL
pyinnotemp-0.2.dist-info/top_level.txt
pyinnotemp-0.2.dist-info/RECORD
