Metadata-Version: 2.1
Name: pyinnotemp
Version: 0.2
Summary: innotemp interface
Home-page: https://github.com/MatthiasHertel80/pyinnotemp
Author: Matthias Hertel
Author-email: matthias.c.hertel@googlemail.com
License: Apache License (2.0)
Keywords: home,automation,innotemp,smarthome
Platform: any
Classifier: Intended Audience :: Developers
Classifier: License :: OSI Approved :: Apache Software License
Classifier: Operating System :: OS Independent
Classifier: Programming Language :: Python :: 3.5
Classifier: Topic :: Home Automation
